{
    "actionOnStepFail": null, 
    "blueprintName": "", 
    "blueprintUuid": "0722c16d-cf7c-42fd-90c2-1bc04aacd598", 
    "cloneUrl": "", 
    "enabled": true, 
    "externalUuid4": "f8c8af25-4a4b-4b14-a248-34f23865a234", 
    "key": "lindeploywin2019unattendedconfigbiosfordriversonxdrivelink", 
    "name": "LIN Deploy Win2019 Unattended Config BIOS for Drivers on X Drive (link)", 
    "parameterMap": [], 
    "projectName": "", 
    "projectUuid": "24a458c3-5025-400b-bb49-4eae2055a149", 
    "projectVersion": "", 
    "type": "com.servertribe.attune.tuples.StepProjectLinkTuple"
}